{
    "original_text": "Poorly differentiated and anaplastic (undifferentiated) carcinomas represent aggressive neoplasms of the thyroid follicular epithelium, cumulatively accounting for less than 5% of thyroid tumors, but with a high mortality rate (approaching 100% for anaplastic lesions). Patients with either carcinoma are older than those with other types of thyroid cancer, with a mean age of 65 years. Approximately one-fourth of patients with poorly differentiated or anaplastic thyroid carcinomas have a past history of a well-differentiated follicular neoplasm, and another one-fourth harbor a concurrent well-differentiated neoplasm in the resected specimen.\n\nMORPHOLOGY\nMicroscopically, poorly differentiated carcinomas are composed of cells with minimal follicular differentiation, arranged in insular or trabecular growth patterns; intratumoral necrosis and frequent mitoses are often seen. Anaplastic carcinomas demonstrate variable morphology, including (1) large, pleomorphic giant cells, including occasional osteoclast-like multinucleate giant cells; (2) spindle cells with a sarcomatous appearance; and (3) mixed spindle and giant cells. Foci of papillary or follicular differentiation may be present in some tumors, suggesting an origin from a well- differentiated carcinoma. The neoplastic cells express epithelial markers like cytokeratin, but are usually negative for markers of thyroid differentiation, like thyroglobulin.\n\nClinical Features\nPoorly differentiated and anaplastic carcinomas usually present as rapidly enlarging bulky neck masses. In most cases, the disease has spread beyond the thyroid into adjacent neck structures or has metastasized to the lungs at the time of presentation. Symptoms related to compression and invasion of adjacent structures, such as dyspnea, dysphagia, hoarseness, and cough, are common. Anaplastic carcinomas of the thyroid are one of the most aggressive cancers known; in most cases death occurs in less than 1 year. Poorly dif- ferentiated carcinomas fare somewhat better with radical surgery, external beam radiotherapy, and radioactive iodine. More recently, immunotherapy using immune checkpoint inhibitors has been used in these neoplasms in an attempt to improve their dire prognosis.",
    "paragraphs": [
        {
            "text": "Poorly differentiated and anaplastic (undifferentiated) carcinomas represent aggressive neoplasms of the thyroid follicular epithelium, cumulatively accounting for less than 5% of thyroid tumors, but with a high mortality rate (approaching 100% for anaplastic lesions). Patients with either carcinoma are older than those with other types of thyroid cancer, with a mean age of 65 years. Approximately one-fourth of patients with poorly differentiated or anaplastic thyroid carcinomas have a past history of a well-differentiated follicular neoplasm, and another one-fourth harbor a concurrent well-differentiated neoplasm in the resected specimen.",
            "stats": {
                "poorly": {
                    "tf": 0.022727272727272728,
                    "idf": 0
                },
                "differentiated": {
                    "tf": 0.045454545454545456,
                    "idf": 0
                },
                "and": {
                    "tf": 0.022727272727272728,
                    "idf": 0
                },
                "anaplastic": {
                    "tf": 0.03409090909090909,
                    "idf": 0
                },
                "undifferentiated": {
                    "tf": 0.011363636363636364,
                    "idf": 0
                },
                "carcinomas": {
                    "tf": 0.022727272727272728,
                    "idf": 0
                },
                "represent": {
                    "tf": 0.011363636363636364,
                    "idf": 0
                },
                "aggressive": {
                    "tf": 0.011363636363636364,
                    "idf": 0
                },
                "neoplasms": {
                    "tf": 0.011363636363636364,
                    "idf": 0
                },
                "of": {
                    "tf": 0.06818181818181818,
                    "idf": 0
                },
                "the": {
                    "tf": 0.022727272727272728,
                    "idf": 0
                },
                "thyroid": {
                    "tf": 0.045454545454545456,
                    "idf": 0
                },
                "follicular": {
                    "tf": 0.022727272727272728,
                    "idf": 0
                },
                "epithelium": {
                    "tf": 0.011363636363636364,
                    "idf": 0
                },
                "cumulatively": {
                    "tf": 0.011363636363636364,
                    "idf": 0
                },
                "accounting": {
                    "tf": 0.011363636363636364,
                    "idf": 0
                },
                "for": {
                    "tf": 0.022727272727272728,
                    "idf": 0
                },
                "less": {
                    "tf": 0.011363636363636364,
                    "idf": 0
                },
                "than": {
                    "tf": 0.022727272727272728,
                    "idf": 0
                },
                "tumors": {
                    "tf": 0.011363636363636364,
                    "idf": 0
                },
                "but": {
                    "tf": 0.011363636363636364,
                    "idf": 0
                },
                "with": {
                    "tf": 0.056818181818181816,
                    "idf": 0
                },
                "a": {
                    "tf": 0.056818181818181816,
                    "idf": 0
                },
                "high": {
                    "tf": 0.011363636363636364,
                    "idf": 0
                },
                "mortality": {
                    "tf": 0.011363636363636364,
                    "idf": 0
                },
                "rate": {
                    "tf": 0.011363636363636364,
                    "idf": 0
                },
                "approaching": {
                    "tf": 0.011363636363636364,
                    "idf": 0
                },
                "lesions": {
                    "tf": 0.011363636363636364,
                    "idf": 0
                },
                "patients": {
                    "tf": 0.022727272727272728,
                    "idf": 0
                },
                "either": {
                    "tf": 0.011363636363636364,
                    "idf": 0
                },
                "carcinoma": {
                    "tf": 0.011363636363636364,
                    "idf": 0
                },
                "are": {
                    "tf": 0.011363636363636364,
                    "idf": 0
                },
                "older": {
                    "tf": 0.011363636363636364,
                    "idf": 0
                },
                "those": {
                    "tf": 0.011363636363636364,
                    "idf": 0
                },
                "other": {
                    "tf": 0.011363636363636364,
                    "idf": 0
                },
                "types": {
                    "tf": 0.011363636363636364,
                    "idf": 0
                },
                "cancer": {
                    "tf": 0.011363636363636364,
                    "idf": 0
                },
                "mean": {
                    "tf": 0.011363636363636364,
                    "idf": 0
                },
                "age": {
                    "tf": 0.011363636363636364,
                    "idf": 0
                },
                "years": {
                    "tf": 0.011363636363636364,
                    "idf": 0
                },
                "approximately": {
                    "tf": 0.011363636363636364,
                    "idf": 0
                },
                "one": {
                    "tf": 0.022727272727272728,
                    "idf": 0
                },
                "fourth": {
                    "tf": 0.022727272727272728,
                    "idf": 0
                },
                "or": {
                    "tf": 0.011363636363636364,
                    "idf": 0
                },
                "have": {
                    "tf": 0.011363636363636364,
                    "idf": 0
                },
                "past": {
                    "tf": 0.011363636363636364,
                    "idf": 0
                },
                "history": {
                    "tf": 0.011363636363636364,
                    "idf": 0
                },
                "well": {
                    "tf": 0.022727272727272728,
                    "idf": 0
                },
                "neoplasm": {
                    "tf": 0.022727272727272728,
                    "idf": 0
                },
                "another": {
                    "tf": 0.011363636363636364,
                    "idf": 0
                },
                "harbor": {
                    "tf": 0.011363636363636364,
                    "idf": 0
                },
                "concurrent": {
                    "tf": 0.011363636363636364,
                    "idf": 0
                },
                "in": {
                    "tf": 0.011363636363636364,
                    "idf": 0
                },
                "resected": {
                    "tf": 0.011363636363636364,
                    "idf": 0
                },
                "specimen": {
                    "tf": 0.011363636363636364,
                    "idf": 0
                }
            }
        },
        {
            "text": "MORPHOLOGY\nMicroscopically, poorly differentiated carcinomas are composed of cells with minimal follicular differentiation, arranged in insular or trabecular growth patterns; intratumoral necrosis and frequent mitoses are often seen. Anaplastic carcinomas demonstrate variable morphology, including (1) large, pleomorphic giant cells, including occasional osteoclast-like multinucleate giant cells; (2) spindle cells with a sarcomatous appearance; and (3) mixed spindle and giant cells. Foci of papillary or follicular differentiation may be present in some tumors, suggesting an origin from a well- differentiated carcinoma. The neoplastic cells express epithelial markers like cytokeratin, but are usually negative for markers of thyroid differentiation, like thyroglobulin.",
            "stats": {
                "morphology": {
                    "tf": 0.020833333333333332,
                    "idf": 0
                },
                "microscopically": {
                    "tf": 0.010416666666666666,
                    "idf": 0
                },
                "poorly": {
                    "tf": 0.010416666666666666,
                    "idf": 0
                },
                "differentiated": {
                    "tf": 0.020833333333333332,
                    "idf": 0
                },
                "carcinomas": {
                    "tf": 0.020833333333333332,
                    "idf": 0
                },
                "are": {
                    "tf": 0.03125,
                    "idf": 0
                },
                "composed": {
                    "tf": 0.010416666666666666,
                    "idf": 0
                },
                "of": {
                    "tf": 0.03125,
                    "idf": 0
                },
                "cells": {
                    "tf": 0.0625,
                    "idf": 0
                },
                "with": {
                    "tf": 0.020833333333333332,
                    "idf": 0
                },
                "minimal": {
                    "tf": 0.010416666666666666,
                    "idf": 0
                },
                "follicular": {
                    "tf": 0.020833333333333332,
                    "idf": 0
                },
                "differentiation": {
                    "tf": 0.03125,
                    "idf": 0
                },
                "arranged": {
                    "tf": 0.010416666666666666,
                    "idf": 0
                },
                "in": {
                    "tf": 0.020833333333333332,
                    "idf": 0
                },
                "insular": {
                    "tf": 0.010416666666666666,
                    "idf": 0
                },
                "or": {
                    "tf": 0.020833333333333332,
                    "idf": 0
                },
                "trabecular": {
                    "tf": 0.010416666666666666,
                    "idf": 0
                },
                "growth": {
                    "tf": 0.010416666666666666,
                    "idf": 0
                },
                "patterns": {
                    "tf": 0.010416666666666666,
                    "idf": 0
                },
                "intratumoral": {
                    "tf": 0.010416666666666666,
                    "idf": 0
                },
                "necrosis": {
                    "tf": 0.010416666666666666,
                    "idf": 0
                },
                "and": {
                    "tf": 0.03125,
                    "idf": 0
                },
                "frequent": {
                    "tf": 0.010416666666666666,
                    "idf": 0
                },
                "mitoses": {
                    "tf": 0.010416666666666666,
                    "idf": 0
                },
                "often": {
                    "tf": 0.010416666666666666,
                    "idf": 0
                },
                "seen": {
                    "tf": 0.010416666666666666,
                    "idf": 0
                },
                "anaplastic": {
                    "tf": 0.010416666666666666,
                    "idf": 0
                },
                "demonstrate": {
                    "tf": 0.010416666666666666,
                    "idf": 0
                },
                "variable": {
                    "tf": 0.010416666666666666,
                    "idf": 0
                },
                "including": {
                    "tf": 0.020833333333333332,
                    "idf": 0
                },
                "large": {
                    "tf": 0.010416666666666666,
                    "idf": 0
                },
                "pleomorphic": {
                    "tf": 0.010416666666666666,
                    "idf": 0
                },
                "giant": {
                    "tf": 0.03125,
                    "idf": 0
                },
                "occasional": {
                    "tf": 0.010416666666666666,
                    "idf": 0
                },
                "osteoclast": {
                    "tf": 0.010416666666666666,
                    "idf": 0
                },
                "like": {
                    "tf": 0.03125,
                    "idf": 0
                },
                "multinucleate": {
                    "tf": 0.010416666666666666,
                    "idf": 0
                },
                "spindle": {
                    "tf": 0.020833333333333332,
                    "idf": 0
                },
                "a": {
                    "tf": 0.020833333333333332,
                    "idf": 0
                },
                "sarcomatous": {
                    "tf": 0.010416666666666666,
                    "idf": 0
                },
                "appearance": {
                    "tf": 0.010416666666666666,
                    "idf": 0
                },
                "mixed": {
                    "tf": 0.010416666666666666,
                    "idf": 0
                },
                "foci": {
                    "tf": 0.010416666666666666,
                    "idf": 0
                },
                "papillary": {
                    "tf": 0.010416666666666666,
                    "idf": 0
                },
                "may": {
                    "tf": 0.010416666666666666,
                    "idf": 0
                },
                "be": {
                    "tf": 0.010416666666666666,
                    "idf": 0
                },
                "present": {
                    "tf": 0.010416666666666666,
                    "idf": 0
                },
                "some": {
                    "tf": 0.010416666666666666,
                    "idf": 0
                },
                "tumors": {
                    "tf": 0.010416666666666666,
                    "idf": 0
                },
                "suggesting": {
                    "tf": 0.010416666666666666,
                    "idf": 0
                },
                "an": {
                    "tf": 0.010416666666666666,
                    "idf": 0
                },
                "origin": {
                    "tf": 0.010416666666666666,
                    "idf": 0
                },
                "from": {
                    "tf": 0.010416666666666666,
                    "idf": 0
                },
                "well": {
                    "tf": 0.010416666666666666,
                    "idf": 0
                },
                "carcinoma": {
                    "tf": 0.010416666666666666,
                    "idf": 0
                },
                "the": {
                    "tf": 0.010416666666666666,
                    "idf": 0
                },
                "neoplastic": {
                    "tf": 0.010416666666666666,
                    "idf": 0
                },
                "express": {
                    "tf": 0.010416666666666666,
                    "idf": 0
                },
                "epithelial": {
                    "tf": 0.010416666666666666,
                    "idf": 0
                },
                "markers": {
                    "tf": 0.020833333333333332,
                    "idf": 0
                },
                "cytokeratin": {
                    "tf": 0.010416666666666666,
                    "idf": 0
                },
                "but": {
                    "tf": 0.010416666666666666,
                    "idf": 0
                },
                "usually": {
                    "tf": 0.010416666666666666,
                    "idf": 0
                },
                "negative": {
                    "tf": 0.010416666666666666,
                    "idf": 0
                },
                "for": {
                    "tf": 0.010416666666666666,
                    "idf": 0
                },
                "thyroid": {
                    "tf": 0.010416666666666666,
                    "idf": 0
                },
                "thyroglobulin": {
                    "tf": 0.010416666666666666,
                    "idf": 0
                }
            }
        },
        {
            "text": "Clinical Features\nPoorly differentiated and anaplastic carcinomas usually present as rapidly enlarging bulky neck masses. In most cases, the disease has spread beyond the thyroid into adjacent neck structures or has metastasized to the lungs at the time of presentation. Symptoms related to compression and invasion of adjacent structures, such as dyspnea, dysphagia, hoarseness, and cough, are common. Anaplastic carcinomas of the thyroid are one of the most aggressive cancers known; in most cases death occurs in less than 1 year. Poorly dif- ferentiated carcinomas fare somewhat better with radical surgery, external beam radiotherapy, and radioactive iodine. More recently, immunotherapy using immune checkpoint inhibitors has been used in these neoplasms in an attempt to improve their dire prognosis.",
            "stats": {
                "clinical": {
                    "tf": 0.008547008547008548,
                    "idf": 0
                },
                "features": {
                    "tf": 0.008547008547008548,
                    "idf": 0
                },
                "poorly": {
                    "tf": 0.017094017094017096,
                    "idf": 0
                },
                "differentiated": {
                    "tf": 0.008547008547008548,
                    "idf": 0
                },
                "and": {
                    "tf": 0.03418803418803419,
                    "idf": 0
                },
                "anaplastic": {
                    "tf": 0.017094017094017096,
                    "idf": 0
                },
                "carcinomas": {
                    "tf": 0.02564102564102564,
                    "idf": 0
                },
                "usually": {
                    "tf": 0.008547008547008548,
                    "idf": 0
                },
                "present": {
                    "tf": 0.008547008547008548,
                    "idf": 0
                },
                "as": {
                    "tf": 0.017094017094017096,
                    "idf": 0
                },
                "rapidly": {
                    "tf": 0.008547008547008548,
                    "idf": 0
                },
                "enlarging": {
                    "tf": 0.008547008547008548,
                    "idf": 0
                },
                "bulky": {
                    "tf": 0.008547008547008548,
                    "idf": 0
                },
                "neck": {
                    "tf": 0.017094017094017096,
                    "idf": 0
                },
                "masses": {
                    "tf": 0.008547008547008548,
                    "idf": 0
                },
                "in": {
                    "tf": 0.042735042735042736,
                    "idf": 0
                },
                "most": {
                    "tf": 0.02564102564102564,
                    "idf": 0
                },
                "cases": {
                    "tf": 0.017094017094017096,
                    "idf": 0
                },
                "the": {
                    "tf": 0.05128205128205128,
                    "idf": 0
                },
                "disease": {
                    "tf": 0.008547008547008548,
                    "idf": 0
                },
                "has": {
                    "tf": 0.02564102564102564,
                    "idf": 0
                },
                "spread": {
                    "tf": 0.008547008547008548,
                    "idf": 0
                },
                "beyond": {
                    "tf": 0.008547008547008548,
                    "idf": 0
                },
                "thyroid": {
                    "tf": 0.017094017094017096,
                    "idf": 0
                },
                "into": {
                    "tf": 0.008547008547008548,
                    "idf": 0
                },
                "adjacent": {
                    "tf": 0.017094017094017096,
                    "idf": 0
                },
                "structures": {
                    "tf": 0.017094017094017096,
                    "idf": 0
                },
                "or": {
                    "tf": 0.008547008547008548,
                    "idf": 0
                },
                "metastasized": {
                    "tf": 0.008547008547008548,
                    "idf": 0
                },
                "to": {
                    "tf": 0.02564102564102564,
                    "idf": 0
                },
                "lungs": {
                    "tf": 0.008547008547008548,
                    "idf": 0
                },
                "at": {
                    "tf": 0.008547008547008548,
                    "idf": 0
                },
                "time": {
                    "tf": 0.008547008547008548,
                    "idf": 0
                },
                "of": {
                    "tf": 0.03418803418803419,
                    "idf": 0
                },
                "presentation": {
                    "tf": 0.008547008547008548,
                    "idf": 0
                },
                "symptoms": {
                    "tf": 0.008547008547008548,
                    "idf": 0
                },
                "related": {
                    "tf": 0.008547008547008548,
                    "idf": 0
                },
                "compression": {
                    "tf": 0.008547008547008548,
                    "idf": 0
                },
                "invasion": {
                    "tf": 0.008547008547008548,
                    "idf": 0
                },
                "such": {
                    "tf": 0.008547008547008548,
                    "idf": 0
                },
                "dyspnea": {
                    "tf": 0.008547008547008548,
                    "idf": 0
                },
                "dysphagia": {
                    "tf": 0.008547008547008548,
                    "idf": 0
                },
                "hoarseness": {
                    "tf": 0.008547008547008548,
                    "idf": 0
                },
                "cough": {
                    "tf": 0.008547008547008548,
                    "idf": 0
                },
                "are": {
                    "tf": 0.017094017094017096,
                    "idf": 0
                },
                "common": {
                    "tf": 0.008547008547008548,
                    "idf": 0
                },
                "one": {
                    "tf": 0.008547008547008548,
                    "idf": 0
                },
                "aggressive": {
                    "tf": 0.008547008547008548,
                    "idf": 0
                },
                "cancers": {
                    "tf": 0.008547008547008548,
                    "idf": 0
                },
                "known": {
                    "tf": 0.008547008547008548,
                    "idf": 0
                },
                "death": {
                    "tf": 0.008547008547008548,
                    "idf": 0
                },
                "occurs": {
                    "tf": 0.008547008547008548,
                    "idf": 0
                },
                "less": {
                    "tf": 0.008547008547008548,
                    "idf": 0
                },
                "than": {
                    "tf": 0.008547008547008548,
                    "idf": 0
                },
                "year": {
                    "tf": 0.008547008547008548,
                    "idf": 0
                },
                "dif": {
                    "tf": 0.008547008547008548,
                    "idf": 0
                },
                "ferentiated": {
                    "tf": 0.008547008547008548,
                    "idf": 0
                },
                "fare": {
                    "tf": 0.008547008547008548,
                    "idf": 0
                },
                "somewhat": {
                    "tf": 0.008547008547008548,
                    "idf": 0
                },
                "better": {
                    "tf": 0.008547008547008548,
                    "idf": 0
                },
                "with": {
                    "tf": 0.008547008547008548,
                    "idf": 0
                },
                "radical": {
                    "tf": 0.008547008547008548,
                    "idf": 0
                },
                "surgery": {
                    "tf": 0.008547008547008548,
                    "idf": 0
                },
                "external": {
                    "tf": 0.008547008547008548,
                    "idf": 0
                },
                "beam": {
                    "tf": 0.008547008547008548,
                    "idf": 0
                },
                "radiotherapy": {
                    "tf": 0.008547008547008548,
                    "idf": 0
                },
                "radioactive": {
                    "tf": 0.008547008547008548,
                    "idf": 0
                },
                "iodine": {
                    "tf": 0.008547008547008548,
                    "idf": 0
                },
                "more": {
                    "tf": 0.008547008547008548,
                    "idf": 0
                },
                "recently": {
                    "tf": 0.008547008547008548,
                    "idf": 0
                },
                "immunotherapy": {
                    "tf": 0.008547008547008548,
                    "idf": 0
                },
                "using": {
                    "tf": 0.008547008547008548,
                    "idf": 0
                },
                "immune": {
                    "tf": 0.008547008547008548,
                    "idf": 0
                },
                "checkpoint": {
                    "tf": 0.008547008547008548,
                    "idf": 0
                },
                "inhibitors": {
                    "tf": 0.008547008547008548,
                    "idf": 0
                },
                "been": {
                    "tf": 0.008547008547008548,
                    "idf": 0
                },
                "used": {
                    "tf": 0.008547008547008548,
                    "idf": 0
                },
                "these": {
                    "tf": 0.008547008547008548,
                    "idf": 0
                },
                "neoplasms": {
                    "tf": 0.008547008547008548,
                    "idf": 0
                },
                "an": {
                    "tf": 0.008547008547008548,
                    "idf": 0
                },
                "attempt": {
                    "tf": 0.008547008547008548,
                    "idf": 0
                },
                "improve": {
                    "tf": 0.008547008547008548,
                    "idf": 0
                },
                "their": {
                    "tf": 0.008547008547008548,
                    "idf": 0
                },
                "dire": {
                    "tf": 0.008547008547008548,
                    "idf": 0
                },
                "prognosis": {
                    "tf": 0.008547008547008548,
                    "idf": 0
                }
            }
        }
    ]
}